teddy/__init__.py
teddy/attr_mapping.py
teddy/compose.py
teddy/dsl.py
teddy/interface.py
teddy/keyed_sequence.py
teddy/popo.py
teddy/transformers.py
teddy/zipper.py
teddy/tests/__init__.py
teddy/tests/test_keyed_sequence.py
teddy/tests/test_teddy.py
teddy/tests/test_transformers.py
teddy-0.0.1.dist-info/LICENSE
teddy-0.0.1.dist-info/METADATA
teddy-0.0.1.dist-info/WHEEL
teddy-0.0.1.dist-info/top_level.txt
teddy-0.0.1.dist-info/RECORD
