Metadata-Version: 2.1
Name: teddy
Version: 0.0.1
Summary: Teddy is like Pandas, but Teddy loves you.
Home-page: https://github.com/blackhc/teddy
Author: Andreas @blackhc Kirsch
Author-email: blackhc+teddy@gmail.com
License: MIT
Keywords: tools pandas data
Platform: UNKNOWN
Classifier: Development Status :: 3 - Alpha
Classifier: Intended Audience :: Developers
Classifier: Intended Audience :: Science/Research
Classifier: Topic :: Software Development :: Libraries :: Python Modules
Classifier: License :: OSI Approved :: MIT License
Classifier: Programming Language :: Python :: 3.7
Provides-Extra: dev
Requires-Dist: check-manifest ; extra == 'dev'
Provides-Extra: test
Requires-Dist: coverage ; extra == 'test'
Requires-Dist: codecov ; extra == 'test'
Requires-Dist: pytest ; extra == 'test'
Requires-Dist: pytest-benchmark ; extra == 'test'
Requires-Dist: pytest-cov ; extra == 'test'
